pygdrive3/__init__.py
pygdrive3/service.py
test/__init__.py
test/addMultipleFileShortcuts.py
test/context.py
test/list.py
test/test.py
pygdrive3-0.8.1.dist-info/LICENSE.md
pygdrive3-0.8.1.dist-info/METADATA
pygdrive3-0.8.1.dist-info/WHEEL
pygdrive3-0.8.1.dist-info/top_level.txt
pygdrive3-0.8.1.dist-info/RECORD
