Metadata-Version: 2.1
Name: pygdrive3
Version: 0.8.1
Summary: Use Google Drive API v3 with a python interface
Home-page: https://github.com/matalmeida/pygdrive3
Author: Matheus Almeida
Author-email: mat.almeida@live.com
License: MIT
Platform: UNKNOWN
Classifier: Programming Language :: Python :: 3
Classifier: License :: OSI Approved :: MIT License
Classifier: Operating System :: OS Independent
